oracle_to_python/__init__.py
oracle_to_python/nulls.py
oracle_to_python-0.0.2.dist-info/LICENSE.txt
oracle_to_python-0.0.2.dist-info/METADATA
oracle_to_python-0.0.2.dist-info/WHEEL
oracle_to_python-0.0.2.dist-info/top_level.txt
oracle_to_python-0.0.2.dist-info/RECORD
