Metadata-Version: 2.1
Name: oracle-to-python
Version: 0.0.2
Summary: Oracle NULL functions equivalent in Oracle
Home-page: https://github.com/pypa/sampleproject
Author: Arun Jaiswal
Author-email: arrrsh@gmail.com
License: UNKNOWN
Platform: UNKNOWN
Classifier: Programming Language :: Python :: 3
Classifier: License :: OSI Approved :: MIT License
Classifier: Operating System :: OS Independent
Classifier: Natural Language :: English
Requires-Python: >=3.6
